argus/__init__.py
argus/compat.py
argus/version.py
argus/auth/__init__.py
argus/auth/admin.py
argus/auth/apps.py
argus/auth/authentication.py
argus/auth/context_processors.py
argus/auth/factories.py
argus/auth/models.py
argus/auth/serializers.py
argus/auth/urls.py
argus/auth/utils.py
argus/auth/views.py
argus/auth/drftoken/__init__.py
argus/auth/drftoken/serializers.py
argus/auth/drftoken/urls.py
argus/auth/drftoken/views.py
argus/auth/knox/__init__.py
argus/auth/knox/serializers.py
argus/auth/knox/urls.py
argus/auth/knox/views.py
argus/auth/management/__init__.py
argus/auth/management/commands/__init__.py
argus/auth/management/commands/changeuser.py
argus/auth/management/commands/createuser.py
argus/auth/management/commands/grantsuperuser.py
argus/auth/management/commands/revokesuperuser.py
argus/auth/management/commands/setpassword.py
argus/auth/migrations/0001_initial.py
argus/auth/migrations/0002_alter_user_first_name.py
argus/auth/migrations/0002_squashed_auth_20250512_add_preferences_model.py
argus/auth/migrations/0003_delete_phonenumber.py
argus/auth/migrations/0004_add_preferences_model.py
argus/auth/migrations/__init__.py
argus/base/__init__.py
argus/base/apps.py
argus/base/static/favicon.svg
argus/base/templates/base.html
argus/base/templates/index.html
argus/dev/__init__.py
argus/dev/apps.py
argus/dev/utils.py
argus/dev/management/__init__.py
argus/dev/management/commands/__init__.py
argus/dev/management/commands/bulk_incidents.py
argus/dev/management/commands/check_token_expiry.py
argus/dev/management/commands/close_incident.py
argus/dev/management/commands/create_fake_incident.py
argus/dev/management/commands/create_source.py
argus/dev/management/commands/gen_secret_key.py
argus/dev/management/commands/initial_setup.py
argus/dev/management/commands/list_filters.py
argus/dev/management/commands/stresstest.py
argus/dev/management/commands/toggle_profile_activation.py
argus/drf/__init__.py
argus/drf/permissions.py
argus/filter/__init__.py
argus_server-2.6.0.dist-info/METADATA
argus_server-2.6.0.dist-info/WHEEL
argus_server-2.6.0.dist-info/licenses/LICENSE
argus_server-2.6.0.dist-info/RECORD
