Metadata-Version: 2.4
Name: argus-server
Version: 2.6.0
Summary: Argus is an alert aggregator for monitoring systems
Project-URL: Homepage, https://github.com/Uninett/Argus
Author-email: Uninett Opensource <opensource@uninett.no>
License: GPL-3.0-or-later
License-File: LICENSE
Classifier: Framework :: Django
Classifier: Framework :: Django :: 5.2
Classifier: Intended Audience :: Information Technology
Classifier: Intended Audience :: System Administrators
Classifier: License :: OSI Approved :: GNU General Public License v3 or later (GPLv3+)
Classifier: Programming Language :: Python :: 3 :: Only
Classifier: Programming Language :: Python :: 3.10
Classifier: Programming Language :: Python :: 3.11
Classifier: Programming Language :: Python :: 3.12
Classifier: Programming Language :: Python :: 3.13
Classifier: Topic :: System :: Monitoring
Requires-Python: >=3.10
Requires-Dist: dj-database-url>=0.5.0
Requires-Dist: django-cors-headers>=3.2
Requires-Dist: django-filter
Requires-Dist: django-htmx
Requires-Dist: django-phonenumber-field[phonenumberslite]
Requires-Dist: django-rest-knox
Requires-Dist: django-widget-tweaks==1.5.0
Requires-Dist: django<6.0,>=5.2
Requires-Dist: djangorestframework>=3.14
Requires-Dist: drf-rw-serializers>=1.1
Requires-Dist: drf-spectacular>=0.17
Requires-Dist: factory-boy
Requires-Dist: fontawesomefree~=6.6
Requires-Dist: httpx
Requires-Dist: psycopg2
Requires-Dist: pydantic>=2
Requires-Dist: python-dataporten-auth
Requires-Dist: social-auth-app-django>=5.0
Requires-Dist: social-auth-core>=4.1
Requires-Dist: wheel
Requires-Dist: whitenoise
Provides-Extra: dev
Requires-Dist: build; extra == 'dev'
Requires-Dist: coverage; extra == 'dev'
Requires-Dist: django-debug-toolbar; extra == 'dev'
Requires-Dist: django-extensions; extra == 'dev'
Requires-Dist: djlint; extra == 'dev'
Requires-Dist: ipython; extra == 'dev'
Requires-Dist: pre-commit; extra == 'dev'
Requires-Dist: python-dotenv; extra == 'dev'
Requires-Dist: ruff; extra == 'dev'
Requires-Dist: towncrier; extra == 'dev'
Requires-Dist: tox>=4; extra == 'dev'
Requires-Dist: werkzeug; extra == 'dev'
Provides-Extra: docs
Requires-Dist: sphinx>=2.2.0; extra == 'docs'
Provides-Extra: htmx
